{
  "flowId": {
    "value": "RESUME_FLOW"
  },
  "firstAction": "CREATE_CONTEXT_ACTION",
  "actions": [
    {
      "actionName": "CREATE_CONTEXT_ACTION",
      "actionType": "FUNCTION",
      "nextAction": {
        "resolver": "FIXED_NEXT_ACTION",
        "parameters": {
          "nextAction": "SEND_CONTEXT_ACTION"
        }
      }
    },
    {
      "actionName": "SEND_CONTEXT_ACTION",
      "actionType": "CONSUMER"
    },
    {
      "actionName": "RESUME_CONTEXT_ACTION",
      "actionType": "RESUME",
      "nextAction": {
        "resolver": "FIXED_NEXT_ACTION",
        "parameters": {
          "nextAction": "LAST_CONTEXT_ACTION"
        }
      }
    },
    {
      "actionName": "LAST_CONTEXT_ACTION",
      "actionType": "CONSUMER",
      "finalAction": true
    }
  ]
}